{"timestamp": "2026-03-26T11:57:16.235403", "name": "Unknown", "success": false, "confidence": 0.0, "security_level": "maximum"}
{"timestamp": "2026-03-26T11:57:16.594793", "name": "Unknown", "success": false, "confidence": 0.0, "security_level": "maximum"}
{"timestamp": "2026-03-26T11:57:16.765282", "name": "Unknown", "success": false, "confidence": 0.0, "security_level": "maximum"}
{"timestamp": "2026-03-26T11:57:16.932182", "name": "Unknown", "success": false, "confidence": 0.0, "security_level": "maximum"}
{"timestamp": "2026-03-26T11:57:17.600485", "name": "Unknown", "success": false, "confidence": 0.0, "security_level": "maximum"}
{"timestamp": "2026-03-26T11:57:17.936037", "name": "Unknown", "success": false, "confidence": 0.0, "security_level": "maximum"}
{"timestamp": "2026-03-26T11:57:18.103559", "name": "Unknown", "success": false, "confidence": 0.0, "security_level": "maximum"}
{"timestamp": "2026-03-26T11:57:18.611473", "name": "Unknown", "success": false, "confidence": 0.0, "security_level": "maximum"}
{"timestamp": "2026-03-26T11:57:18.958729", "name": "Unknown", "success": false, "confidence": 0.0, "security_level": "maximum"}
{"timestamp": "2026-03-26T11:57:19.293997", "name": "Unknown", "success": false, "confidence": 0.0, "security_level": "maximum"}
{"timestamp": "2026-03-26T11:57:19.964354", "name": "Unknown", "success": false, "confidence": 0.0, "security_level": "maximum"}
{"timestamp": "2026-03-26T11:57:20.132192", "name": "Unknown", "success": false, "confidence": 0.0, "security_level": "maximum"}
{"timestamp": "2026-03-26T11:57:20.636987", "name": "Unknown", "success": false, "confidence": 0.0, "security_level": "maximum"}
{"timestamp": "2026-03-26T11:57:20.971735", "name": "Unknown", "success": false, "confidence": 0.0, "security_level": "maximum"}
{"timestamp": "2026-03-26T11:57:21.305951", "name": "Unknown", "success": false, "confidence": 0.0, "security_level": "maximum"}
{"timestamp": "2026-03-26T11:57:21.473028", "name": "Unknown", "success": false, "confidence": 0.0, "security_level": "maximum"}
{"timestamp": "2026-03-26T11:57:21.807603", "name": "Unknown", "success": false, "confidence": 0.0, "security_level": "maximum"}
{"timestamp": "2026-03-26T11:57:21.974345", "name": "Unknown", "success": false, "confidence": 0.0, "security_level": "maximum"}
{"timestamp": "2026-03-26T11:57:22.140943", "name": "Unknown", "success": false, "confidence": 0.0, "security_level": "maximum"}
{"timestamp": "2026-03-26T11:57:22.474849", "name": "Unknown", "success": false, "confidence": 0.0, "security_level": "maximum"}
{"timestamp": "2026-03-26T11:57:23.140786", "name": "Unknown", "success": false, "confidence": 0.0, "security_level": "maximum"}
{"timestamp": "2026-03-26T11:57:23.309524", "name": "Unknown", "success": false, "confidence": 0.0, "security_level": "maximum"}
{"timestamp": "2026-03-26T11:57:23.477896", "name": "Unknown", "success": false, "confidence": 0.0, "security_level": "maximum"}
{"timestamp": "2026-03-26T11:57:23.813787", "name": "Unknown", "success": false, "confidence": 0.0, "security_level": "maximum"}
{"timestamp": "2026-03-26T11:57:23.980754", "name": "Unknown", "success": false, "confidence": 0.0, "security_level": "maximum"}
{"timestamp": "2026-03-26T11:57:24.647677", "name": "Unknown", "success": false, "confidence": 0.0, "security_level": "maximum"}
{"timestamp": "2026-03-26T11:57:25.148513", "name": "Unknown", "success": false, "confidence": 0.0, "security_level": "maximum"}
{"timestamp": "2026-03-26T11:57:25.315670", "name": "Unknown", "success": false, "confidence": 0.0, "security_level": "maximum"}
{"timestamp": "2026-03-26T11:57:25.483318", "name": "Unknown", "success": false, "confidence": 0.0, "security_level": "maximum"}
{"timestamp": "2026-03-26T11:57:25.650562", "name": "Unknown", "success": false, "confidence": 0.0, "security_level": "maximum"}
{"timestamp": "2026-03-26T11:57:26.317924", "name": "Unknown", "success": false, "confidence": 0.0, "security_level": "maximum"}
{"timestamp": "2026-03-26T11:57:27.318917", "name": "Unknown", "success": false, "confidence": 0.0, "security_level": "maximum"}
{"timestamp": "2026-03-26T11:57:27.822339", "name": "Unknown", "success": false, "confidence": 0.0, "security_level": "maximum"}
{"timestamp": "2026-03-26T11:57:28.157034", "name": "Unknown", "success": false, "confidence": 0.0, "security_level": "maximum"}
{"timestamp": "2026-03-26T11:57:28.662848", "name": "Unknown", "success": false, "confidence": 0.0, "security_level": "maximum"}
{"timestamp": "2026-03-26T11:57:30.686726", "name": "Unknown", "success": false, "confidence": 0.0, "security_level": "maximum"}
{"timestamp": "2026-03-26T11:57:30.857959", "name": "Unknown", "success": false, "confidence": 0.0, "security_level": "maximum"}
{"timestamp": "2026-03-26T11:57:31.195939", "name": "Unknown", "success": false, "confidence": 0.0, "security_level": "maximum"}
{"timestamp": "2026-03-26T11:57:31.533637", "name": "Unknown", "success": false, "confidence": 0.0, "security_level": "maximum"}
{"timestamp": "2026-03-26T11:57:36.879923", "name": "Unknown", "success": false, "confidence": 0.0, "security_level": "maximum"}
{"timestamp": "2026-03-26T11:57:37.214541", "name": "Unknown", "success": false, "confidence": 0.0, "security_level": "maximum"}
{"timestamp": "2026-03-26T11:57:37.382227", "name": "Unknown", "success": false, "confidence": 0.0, "security_level": "maximum"}
{"timestamp": "2026-03-26T11:57:37.716349", "name": "Unknown", "success": false, "confidence": 0.0, "security_level": "maximum"}
{"timestamp": "2026-03-26T11:57:38.049386", "name": "Unknown", "success": false, "confidence": 0.0, "security_level": "maximum"}
{"timestamp": "2026-03-26T11:57:41.558797", "name": "Unknown", "success": false, "confidence": 0.0, "security_level": "maximum"}
{"timestamp": "2026-03-26T11:57:41.734117", "name": "Unknown", "success": false, "confidence": 0.0, "security_level": "maximum"}
{"timestamp": "2026-03-26T11:57:42.092560", "name": "Unknown", "success": false, "confidence": 0.0, "security_level": "maximum"}
{"timestamp": "2026-03-26T11:57:43.281390", "name": "Unknown", "success": false, "confidence": 0.0, "security_level": "maximum"}
{"timestamp": "2026-03-26T11:57:43.958119", "name": "Unknown", "success": false, "confidence": 0.0, "security_level": "maximum"}
{"timestamp": "2026-03-26T11:57:44.959220", "name": "Unknown", "success": false, "confidence": 0.0, "security_level": "maximum"}
{"timestamp": "2026-03-26T11:57:45.127116", "name": "Unknown", "success": false, "confidence": 0.0, "security_level": "maximum"}
{"timestamp": "2026-03-26T11:57:45.627367", "name": "Unknown", "success": false, "confidence": 0.0, "security_level": "maximum"}
{"timestamp": "2026-03-26T11:57:45.793826", "name": "Unknown", "success": false, "confidence": 0.0, "security_level": "maximum"}
{"timestamp": "2026-03-26T11:57:46.132589", "name": "Unknown", "success": false, "confidence": 0.0, "security_level": "maximum"}
{"timestamp": "2026-03-26T11:57:47.327334", "name": "Unknown", "success": false, "confidence": 0.0, "security_level": "maximum"}
{"timestamp": "2026-03-26T11:57:49.690953", "name": "Unknown", "success": false, "confidence": 0.0, "security_level": "maximum"}
{"timestamp": "2026-03-26T11:57:49.859774", "name": "Unknown", "success": false, "confidence": 0.0, "security_level": "maximum"}
{"timestamp": "2026-03-26T11:57:50.029659", "name": "Unknown", "success": false, "confidence": 0.0, "security_level": "maximum"}
{"timestamp": "2026-03-26T11:57:50.883157", "name": "Unknown", "success": false, "confidence": 0.0, "security_level": "maximum"}
{"timestamp": "2026-03-26T11:57:51.388126", "name": "Unknown", "success": false, "confidence": 0.0, "security_level": "maximum"}
{"timestamp": "2026-03-26T11:57:52.223256", "name": "Unknown", "success": false, "confidence": 0.0, "security_level": "maximum"}
{"timestamp": "2026-03-26T11:57:52.390318", "name": "Unknown", "success": false, "confidence": 0.0, "security_level": "maximum"}
{"timestamp": "2026-03-26T11:57:52.559253", "name": "Unknown", "success": false, "confidence": 0.0, "security_level": "maximum"}
{"timestamp": "2026-03-26T11:57:52.727032", "name": "Unknown", "success": false, "confidence": 0.0, "security_level": "maximum"}
{"timestamp": "2026-03-26T11:57:53.232085", "name": "Unknown", "success": false, "confidence": 0.0, "security_level": "maximum"}
{"timestamp": "2026-03-26T11:57:53.738957", "name": "Unknown", "success": false, "confidence": 0.0, "security_level": "maximum"}
{"timestamp": "2026-03-26T11:57:53.909531", "name": "Unknown", "success": false, "confidence": 0.0, "security_level": "maximum"}
{"timestamp": "2026-03-26T11:57:54.412779", "name": "Unknown", "success": false, "confidence": 0.0, "security_level": "maximum"}
{"timestamp": "2026-03-26T11:57:54.579415", "name": "Unknown", "success": false, "confidence": 0.0, "security_level": "maximum"}
{"timestamp": "2026-03-26T11:57:55.083843", "name": "Unknown", "success": false, "confidence": 0.0, "security_level": "maximum"}
{"timestamp": "2026-03-26T11:57:55.779781", "name": "Unknown", "success": false, "confidence": 0.0, "security_level": "maximum"}
{"timestamp": "2026-03-26T11:57:56.113820", "name": "Unknown", "success": false, "confidence": 0.0, "security_level": "maximum"}
{"timestamp": "2026-03-26T11:57:56.960804", "name": "Unknown", "success": false, "confidence": 0.0, "security_level": "maximum"}
{"timestamp": "2026-03-26T11:57:57.314659", "name": "Unknown", "success": false, "confidence": 0.0, "security_level": "maximum"}
{"timestamp": "2026-03-26T11:57:58.499257", "name": "Unknown", "success": false, "confidence": 0.0, "security_level": "maximum"}
{"timestamp": "2026-03-26T11:57:58.666412", "name": "Unknown", "success": false, "confidence": 0.0, "security_level": "maximum"}
{"timestamp": "2026-03-26T11:58:02.363424", "name": "Unknown", "success": false, "confidence": 0.0, "security_level": "maximum"}
{"timestamp": "2026-03-26T11:58:04.219967", "name": "Unknown", "success": false, "confidence": 0.0, "security_level": "maximum"}
{"timestamp": "2026-03-26T11:58:05.053710", "name": "Unknown", "success": false, "confidence": 0.0, "security_level": "maximum"}
{"timestamp": "2026-03-26T11:58:05.723046", "name": "Unknown", "success": false, "confidence": 0.0, "security_level": "maximum"}
{"timestamp": "2026-03-26T11:58:06.726236", "name": "Unknown", "success": false, "confidence": 0.0, "security_level": "maximum"}
{"timestamp": "2026-03-26T11:58:07.060309", "name": "Unknown", "success": false, "confidence": 0.0, "security_level": "maximum"}
{"timestamp": "2026-03-26T11:58:07.896774", "name": "Unknown", "success": false, "confidence": 0.0, "security_level": "maximum"}
{"timestamp": "2026-03-26T11:58:08.064526", "name": "Unknown", "success": false, "confidence": 0.0, "security_level": "maximum"}
{"timestamp": "2026-03-26T11:58:08.565855", "name": "Unknown", "success": false, "confidence": 0.0, "security_level": "maximum"}
{"timestamp": "2026-03-26T11:58:09.069430", "name": "Unknown", "success": false, "confidence": 0.0, "security_level": "maximum"}
{"timestamp": "2026-03-26T11:58:10.739263", "name": "Unknown", "success": false, "confidence": 0.0, "security_level": "maximum"}
{"timestamp": "2026-03-26T11:58:11.072703", "name": "Unknown", "success": false, "confidence": 0.0, "security_level": "maximum"}
{"timestamp": "2026-03-26T11:58:11.241002", "name": "Unknown", "success": false, "confidence": 0.0, "security_level": "maximum"}
